image_lite/__init__.py
image_lite/admin.py
image_lite/admins.py
image_lite/apps.py
image_lite/checks.py
image_lite/constants.py
image_lite/decorators.py
image_lite/filters.py
image_lite/filters_pillow.py
image_lite/filters_wand.py
image_lite/form_fields.py
image_lite/image_ops_pillow.py
image_lite/image_ops_wand.py
image_lite/model_fields.py
image_lite/model_mixins.py
image_lite/models.py
image_lite/module_loading.py
image_lite/module_utils.py
image_lite/registry.py
image_lite/tests.py
image_lite/utils.py
image_lite/validators.py
image_lite/views.py
image_lite/management/commands/common.py
image_lite/management/commands/image_create_bulk.py
image_lite/management/commands/image_delete_bulk.py
image_lite/management/commands/image_list.py
image_lite/management/commands/image_sync.py
image_lite/management/commands/reform_create.py
image_lite/management/commands/reform_delete.py
image_lite/management/commands/reform_list.py
image_lite/migrations/__init__.py
image_lite/templates/image/image_detail.html
image_lite/templates/image/reforms_addform.html
image_lite/templatetags/__init__.py
image_lite/templatetags/img_tags.py
django_image_lite-1.7.1.dist-info/LICENSE
django_image_lite-1.7.1.dist-info/WHEEL
django_image_lite-1.7.1.dist-info/METADATA
django_image_lite-1.7.1.dist-info/RECORD
