Metadata-Version: 2.1
Name: django_image_lite
Version: 1.7.1
Summary: Local image handling for Django. Unobtusive, with multiple repositories, powerful filter system and scaleable data.
Author-email: robert crowther <rw.crowther@gmail.com>
Classifier: Operating System :: OS Independent
Classifier: License :: OSI Approved :: BSD License
Classifier: Programming Language :: Python :: 3
Classifier: Framework :: Django
Requires-Dist: pillow
Project-URL: Documentation, https://github.com/rcrowther/django-image-lite
